{
  "indexes": [
    {
      "collectionGroup": "palenques",
      "queryScope": "COLLECTION",
      "fields": [
        {
          "fieldPath": "active",
          "order": "ASCENDING"
        },
        {
          "fieldPath": "creationDate",
          "order": "DESCENDING"
        }
      ]
    },
    {
      "collectionGroup": "events",
      "queryScope": "COLLECTION",
      "fields": [
        {
          "fieldPath": "palenqueId",
          "order": "ASCENDING"
        },
        {
          "fieldPath": "date",
          "order": "DESCENDING"
        }
      ]
    },
    {
      "collectionGroup": "events",
      "queryScope": "COLLECTION",
      "fields": [
        {
          "fieldPath": "date",
          "order": "ASCENDING"
        },
        {
          "fieldPath": "status",
          "order": "ASCENDING"
        }
      ]
    },
    {
      "collectionGroup": "fights",
      "queryScope": "COLLECTION",
      "fields": [
        {
          "fieldPath": "eventId",
          "order": "ASCENDING"
        },
        {
          "fieldPath": "fightNumber",
          "order": "ASCENDING"
        }
      ]
    }
  ],
  "fieldOverrides": []
}
